<annotation>
	<folder>train</folder>
	<filename>exp4.png</filename>
	<path>D:\SharedLinux_D\CPSC_597\Object_Detection_Expressions\dataset\train\exp4.png</path>
	<source>
		<database>Unknown</database>
	</source>
	<size>
		<width>320</width>
		<height>320</height>
		<depth>1</depth>
	</size>
	<segmented>0</segmented>
	<object>
		<name>char</name>
		<pose>Unspecified</pose>
		<truncated>0</truncated>
		<difficult>0</difficult>
		<bndbox>
			<xmin>8</xmin>
			<ymin>140</ymin>
			<xmax>33</xmax>
			<ymax>175</ymax>
		</bndbox>
	</object>
	<object>
		<name>char</name>
		<pose>Unspecified</pose>
		<truncated>0</truncated>
		<difficult>0</difficult>
		<bndbox>
			<xmin>79</xmin>
			<ymin>145</ymin>
			<xmax>102</xmax>
			<ymax>171</ymax>
		</bndbox>
	</object>
	<object>
		<name>char</name>
		<pose>Unspecified</pose>
		<truncated>0</truncated>
		<difficult>0</difficult>
		<bndbox>
			<xmin>141</xmin>
			<ymin>140</ymin>
			<xmax>164</xmax>
			<ymax>174</ymax>
		</bndbox>
	</object>
	<object>
		<name>char</name>
		<pose>Unspecified</pose>
		<truncated>0</truncated>
		<difficult>0</difficult>
		<bndbox>
			<xmin>204</xmin>
			<ymin>151</ymin>
			<xmax>231</xmax>
			<ymax>166</ymax>
		</bndbox>
	</object>
	<object>
		<name>char</name>
		<pose>Unspecified</pose>
		<truncated>0</truncated>
		<difficult>0</difficult>
		<bndbox>
			<xmin>272</xmin>
			<ymin>144</ymin>
			<xmax>307</xmax>
			<ymax>164</ymax>
		</bndbox>
	</object>
</annotation>
